channel_attention/__init__.py
channel_attention/channel_attention.py
channel_attention/conv_block_attention.py
channel_attention/efficient_channel_attention.py
channel_attention/local_attention.py
channel_attention/spatial_attention.py
channel_attention/squeeze_excitation.py
channel_attention/utils.py
channel_attention-0.0.1.dist-info/licenses/LICENSE
channel_attention-0.0.1.dist-info/METADATA
channel_attention-0.0.1.dist-info/WHEEL
channel_attention-0.0.1.dist-info/top_level.txt
channel_attention-0.0.1.dist-info/RECORD
